prepdir-0.18.0.dist-info/METADATA
prepdir-0.18.0.dist-info/WHEEL
prepdir-0.18.0.dist-info/entry_points.txt
prepdir-0.18.0.dist-info/licenses/LICENSE
prepdir/__init__.py
prepdir/config.py
prepdir/config.yaml
prepdir/glob_translate.py
prepdir/is_excluded_file.py
prepdir/main.py
prepdir/prepdir_file_entry.py
prepdir/prepdir_logging.py
prepdir/prepdir_output_file.py
prepdir/prepdir_processor.py
prepdir/scrub_uuids.py
prepdir-0.18.0.dist-info/RECORD
