Metadata-Version: 2.1
Name: prepdir
Version: 0.18.0
Summary: Directory traversal utility to prepare project contents for review
Keywords: ai,artificial intelligence,code review,directory traversal,file content,project documentation,code sharing,developer tools,large language models,llm,project structure
Author-Email: eyecantell <paul@pneuma.solutions>
License: MIT
Classifier: Programming Language :: Python :: 3.9
Classifier: Programming Language :: Python :: 3.10
Classifier: Programming Language :: Python :: 3.11
Classifier: Programming Language :: Python :: 3.12
Classifier: Programming Language :: Python :: 3.13
Classifier: License :: OSI Approved :: MIT License
Classifier: Operating System :: OS Independent
Classifier: Environment :: Console
Classifier: Intended Audience :: Developers
Classifier: Intended Audience :: Education
Classifier: Topic :: Software Development
Classifier: Topic :: Software Development :: Libraries :: Python Modules
Classifier: Topic :: Utilities
Classifier: Topic :: Text Processing :: Markup
Classifier: Development Status :: 4 - Beta
Project-URL: Repository, https://github.com/eyecantell/prepdir
Project-URL: Issues, https://github.com/eyecantell/prepdir/issues
Project-URL: Documentation, https://github.com/eyecantell/prepdir#readme
Requires-Python: >=3.9
Requires-Dist: typing-extensions<5.0,>=4.7.1; python_version < "3.11"
Requires-Dist: pydantic>=2.5.0
Requires-Dist: pyyaml<7.0,>=6.0
Requires-Dist: dynaconf<4.0,>=3.2.6
Provides-Extra: test
Requires-Dist: pytest>=7.4.4; extra == "test"
Requires-Dist: pytest-cov>=4.1.0; extra == "test"
Requires-Dist: coverage>=7.2.7; extra == "test"
